realize/__init__.py
realize/_version.py
realize/auth.py
realize/client.py
realize/config.py
realize/models.py
realize/py.typed
realize/realize_server.py
realize/tools/__init__.py
realize/tools/account_handlers.py
realize/tools/auth_handlers.py
realize/tools/campaign_handlers.py
realize/tools/registry.py
realize/tools/report_handlers.py
realize/tools/utils.py
realize_mcp-1.0.7.dist-info/licenses/LICENSE
realize_mcp-1.0.7.dist-info/METADATA
realize_mcp-1.0.7.dist-info/WHEEL
realize_mcp-1.0.7.dist-info/entry_points.txt
realize_mcp-1.0.7.dist-info/top_level.txt
realize_mcp-1.0.7.dist-info/RECORD
