Metadata-Version: 2.4
Name: realize-mcp
Version: 1.0.7
Summary: MCP server for Taboola's Realize API - campaign analysis and reporting
Author-email: Vladi Manaev <vladi.m@taboola.com>
License-Expression: Apache-2.0
Project-URL: Homepage, https://github.com/taboola/realize-mcp
Project-URL: Repository, https://github.com/taboola/realize-mcp
Project-URL: Documentation, https://github.com/taboola/realize-mcp#readme
Project-URL: Bug Tracker, https://github.com/taboola/realize-mcp/issues
Keywords: mcp,taboola,realize,advertising,campaigns,ai
Classifier: Development Status :: 4 - Beta
Classifier: Programming Language :: Python :: 3
Classifier: Programming Language :: Python :: 3.10
Classifier: Programming Language :: Python :: 3.11
Classifier: Programming Language :: Python :: 3.12
Classifier: Topic :: Software Development :: Libraries :: Python Modules
Classifier: Topic :: Internet :: WWW/HTTP :: Dynamic Content
Classifier: Operating System :: OS Independent
Requires-Python: >=3.10
License-File: LICENSE
Requires-Dist: mcp>=1.0.0
Requires-Dist: httpx>=0.25.0
Requires-Dist: pydantic>=2.0.0
Requires-Dist: python-dotenv>=1.0.0
Dynamic: license-file
